urpaform/__about__.py
urpaform/__init__.py
urpaform/elements.py
urpaform/form.py
urpaform-0.2.0.dist-info/LICENSE
urpaform-0.2.0.dist-info/METADATA
urpaform-0.2.0.dist-info/WHEEL
urpaform-0.2.0.dist-info/top_level.txt
urpaform-0.2.0.dist-info/RECORD
