Metadata-Version: 2.1
Name: urpaform
Version: 0.2.0
Summary: Form Filling Module with UltimateRPA
Home-page: https://github.com/ultimaterpa/urpaform
Author: anerold
Author-email: support@ultimaterpa.cz
License: MIT
Keywords: Robotic Process Automation,RPA,UltimateRPA,form filling
Platform: UNKNOWN
Classifier: Intended Audience :: Developers
Classifier: Programming Language :: Python :: 3.7
Classifier: Operating System :: Microsoft :: Windows
Classifier: License :: OSI Approved :: MIT License
Requires-Python: >=3.7
